setup.py
m2mdict/__init__.py
m2mdict/_common.py
m2mdict/_m2mdict.py
m2mdict/test.py
m2mdict/util.py
m2mdict.egg-info/PKG-INFO
m2mdict.egg-info/SOURCES.txt
m2mdict.egg-info/dependency_links.txt
m2mdict.egg-info/top_level.txt