Metadata-Version: 1.0
Name: m2mdict
Version: 0.0.2
Summary: a datastruct of many to many
Home-page: UNKNOWN
Author: dengjing
Author-email: chinadengjing@gmail.com
License: MIT License
Keywords: map,dict,many to many
Platform: any
